rubin/gafaelfawr/__init__.py
rubin/gafaelfawr/_client.py
rubin/gafaelfawr/_constants.py
rubin/gafaelfawr/_dependencies.py
rubin/gafaelfawr/_exceptions.py
rubin/gafaelfawr/_mock.py
rubin/gafaelfawr/_models.py
rubin/gafaelfawr/_tokens.py
rubin/gafaelfawr/py.typed
rubin_gafaelfawr-15.2.1.dist-info/licenses/LICENSE
rubin_gafaelfawr-15.2.1.dist-info/METADATA
rubin_gafaelfawr-15.2.1.dist-info/WHEEL
rubin_gafaelfawr-15.2.1.dist-info/top_level.txt
rubin_gafaelfawr-15.2.1.dist-info/RECORD
